contrib/delete_old.py
edxbackup/__init__.py
edxbackup/backup.py
edxbackup/cli.py
edxbackup/config.py
edxbackup/context.py
edxbackup/info.py
edxbackup/mongo.py
edxbackup/mysql.py
edxbackup/options.py
edxbackup/postgresql.py
edxbackup/restore.py
edxbackup/s3.py
edxbackup/utils.py
edxbackup/restic/backup.py
edxbackup/restic/restore.py
edxbackup/restic/snapshot.py
example/edxbackup.json
systemd/edxbackup.service
systemd/edxbackup.timer
tests/README.md
tests/docker-compose.yml
tests/edxbackup.json
tests/integration.sh
tests/populate.sh
tests/retention.py
tests/testenv.sh
edxbackup-3.2.1.dist-info/LICENSE
edxbackup-3.2.1.dist-info/METADATA
edxbackup-3.2.1.dist-info/WHEEL
edxbackup-3.2.1.dist-info/entry_points.txt
edxbackup-3.2.1.dist-info/top_level.txt
edxbackup-3.2.1.dist-info/RECORD
