Metadata-Version: 2.1
Name: edxbackup
Version: 3.2.1
Summary: My package description
Author-email: Illia Shestakov <i.shestakov@abstract-technology.de>
License: Apache-2.0
Requires-Python: >=3.11
License-File: LICENSE
Requires-Dist: click
Requires-Dist: pydantic
Requires-Dist: s3ball (>=0.1.1)
